{"data_view":{"id":"0c85bb05-cbd1-4dc8-94f6-3198d459f5c5","version":"WzUsMV0=","title":"sensor-data","timeFieldName":"event_time","sourceFilters":[],"fields":{"_id":{"count":0,"name":"_id","type":"string","esTypes":["_id"],"scripted":false,"searchable":true,"aggregatable":false,"readFromDocValues":false,"format":{"id":"string"},"shortDotsEnable":false,"isMapped":true},"_index":{"count":0,"name":"_index","type":"string","esTypes":["_index"],"scripted":false,"searchable":true,"aggregatable":true,"readFromDocValues":false,"format":{"id":"string"},"shortDotsEnable":false,"isMapped":true},"_score":{"count":0,"name":"_score","type":"number","scripted":false,"searchable":false,"aggregatable":false,"readFromDocValues":false,"format":{"id":"number"},"shortDotsEnable":false,"isMapped":true},"_source":{"count":0,"name":"_source","type":"_source","esTypes":["_source"],"scripted":false,"searchable":false,"aggregatable":false,"readFromDocValues":false,"format":{"id":"_source"},"shortDotsEnable":false,"isMapped":true},"event_id":{"count":0,"name":"event_id","type":"string","esTypes":["keyword"],"scripted":false,"searchable":true,"aggregatable":true,"readFromDocValues":true,"format":{"id":"string"},"shortDotsEnable":false,"isMapped":true},"event_time":{"count":0,"name":"event_time","type":"date","esTypes":["date"],"scripted":false,"searchable":true,"aggregatable":true,"readFromDocValues":true,"format":{"id":"date"},"shortDotsEnable":false,"isMapped":true},"geolocation":{"count":0,"name":"geolocation","type":"geo_point","esTypes":["geo_point"],"scripted":false,"searchable":true,"aggregatable":true,"readFromDocValues":true,"format":{"id":"geo_point","params":{"transform":"wkt"}},"shortDotsEnable":false,"isMapped":true},"latitude":{"count":0,"name":"latitude","type":"number","esTypes":["float"],"scripted":false,"searchable":true,"aggregatable":true,"readFromDocValues":true,"format":{"id":"number"},"shortDotsEnable":false,"isMapped":true},"longitude":{"count":0,"name":"longitude","type":"number","esTypes":["float"],"scripted":false,"searchable":true,"aggregatable":true,"readFromDocValues":true,"format":{"id":"number"},"shortDotsEnable":false,"isMapped":true},"sensor_id":{"count":0,"name":"sensor_id","type":"string","esTypes":["keyword"],"scripted":false,"searchable":true,"aggregatable":true,"readFromDocValues":true,"format":{"id":"string"},"shortDotsEnable":false,"isMapped":true},"sensor_name":{"count":0,"name":"sensor_name","type":"string","esTypes":["text"],"scripted":false,"searchable":true,"aggregatable":false,"readFromDocValues":false,"format":{"id":"string"},"shortDotsEnable":false,"isMapped":true},"sensor_type":{"count":0,"name":"sensor_type","type":"string","esTypes":["keyword"],"scripted":false,"searchable":true,"aggregatable":true,"readFromDocValues":true,"format":{"id":"string"},"shortDotsEnable":false,"isMapped":true}},"fieldFormats":{},"runtimeFieldMap":{},"fieldAttrs":{},"allowNoIndex":false,"name":"sensor-data-view","allowHidden":false,"namespaces":["default"]}}